[
  {
    "nome": "Rw Torres Ltda",
    "categoria": "website",
    "descricao": "Lorem Ipsum",
    "image": "/fundo1.jpg",
    "link": "/teste"
  },
  {
    "nome": "Rw Torres Ltda",
    "categoria": "sistema",
    "descricao": "Lorem Ipsum",
    "image": "/fundo1.jpg",
    "link": "/teste"
  },
  {
    "nome": "Rw Torres Ltda",
    "categoria": "ebook",
    "descricao": "Lorem Ipsum",
    "image": "/fundo1.jpg",
    "link": "/teste"
  },
  {
    "nome": "Rw Torres Ltda - Loja",
    "categoria": "loja-virtual",
    "descricao": "Lorem Ipsum",
    "image": "/fundo1.jpg",
    "link": "/teste"
  },
  {
    "nome": "Rw Torres Ltda",
    "categoria": "website",
    "descricao": "Lorem Ipsum",
    "image": "/fundo1.jpg",
    "link": "/teste"
  }
]